.DS_Store
UCTB/.DS_Store
UCTB/__init__.py
UCTB/dataset/__init__.py
UCTB/dataset/context_loader.py
UCTB/dataset/data_loader.py
UCTB/dataset/dataset.py
UCTB/evaluation/__init__.py
UCTB/evaluation/metric.py
UCTB/model/AGCRN.py
UCTB/model/ARIMA.py
UCTB/model/ASTGCN.py
UCTB/model/DCRNN.py
UCTB/model/DeepST.py
UCTB/model/GMAN.py
UCTB/model/GeoMAN.py
UCTB/model/GraphWaveNet.py
UCTB/model/HM.py
UCTB/model/HMM.py
UCTB/model/MCSTGCN.py
UCTB/model/STGCN.py
UCTB/model/STMeta.py
UCTB/model/STSGCN.py
UCTB/model/ST_MGCN.py
UCTB/model/ST_ResNet.py
UCTB/model/XGBoost.py
UCTB/model/__init__.py
UCTB/model_unit/BaseModel.py
UCTB/model_unit/DCRNN_CELL.py
UCTB/model_unit/GraphModelLayers.py
UCTB/model_unit/ST_RNN.py
UCTB/model_unit/__init__.py
UCTB/preprocess/GraphGenerator.py
UCTB/preprocess/__init__.py
UCTB/preprocess/dataset_helper.py
UCTB/preprocess/preprocessor.py
UCTB/preprocess/time_utils.py
UCTB/train/EarlyStopping.py
UCTB/train/LossFunction.py
UCTB/train/MiniBatchTrain.py
UCTB/train/__init__.py
UCTB/utils/__init__.py
UCTB/utils/make_predict_dataset.py
UCTB/utils/multi_threads.py
UCTB/utils/utils_AGCRN.py
UCTB/utils/utils_ASTGCN.py
UCTB/utils/utils_GMAN.py
UCTB/utils/utils_GraphWaveNet.py
UCTB/utils/utils_STGCN.py
UCTB/utils/utils_STSGCN.py
UCTB-0.3.5.dist-info/LICENSE
UCTB-0.3.5.dist-info/METADATA
UCTB-0.3.5.dist-info/WHEEL
UCTB-0.3.5.dist-info/top_level.txt
UCTB-0.3.5.dist-info/RECORD
