Metadata-Version: 2.1
Name: UCTB
Version: 0.3.5
Summary: Urban Computing ToolBox
Home-page: https://github.com/uctb/UCTB
Author: UCTB group
Author-email: chenliyue2019@gmail.com
License: UNKNOWN
Platform: UNKNOWN
Classifier: Programming Language :: Python :: 3
Classifier: License :: OSI Approved :: MIT License
Classifier: Operating System :: OS Independent
Requires-Dist: hmmlearn (>=0.2.1)
Requires-Dist: keras (==2.2.4)
Requires-Dist: GPUtil
Requires-Dist: numpy (>=1.16.2)
Requires-Dist: pandas (>=0.24.2)
Requires-Dist: python-dateutil
Requires-Dist: scikit-learn (>=0.20.3)
Requires-Dist: scipy (==1.2.1)
Requires-Dist: statsmodels (>=0.9.0)
Requires-Dist: wget (>=3.2)
Requires-Dist: xgboost (>=0.82)
Requires-Dist: nni (>=0.8)
Requires-Dist: chinesecalendar (>=1.2.2)
Requires-Dist: workalendar (>=8.2.0)
Requires-Dist: PyYAML (>=5.1.1)
